alicia_d_sdk/__init__.py
alicia_d_sdk/api/__init__.py
alicia_d_sdk/api/synria_robot_api.py
alicia_d_sdk/execution/__init__.py
alicia_d_sdk/execution/drag_teaching.py
alicia_d_sdk/execution/hardware_executor.py
alicia_d_sdk/execution/sparkvis.py
alicia_d_sdk/hardware/__init__.py
alicia_d_sdk/hardware/data_parser.py
alicia_d_sdk/hardware/serial_comm.py
alicia_d_sdk/hardware/servo_driver.py
alicia_d_sdk/utils/__init__.py
alicia_d_sdk/utils/calculate.py
alicia_d_sdk/utils/logger/__init__.py
alicia_d_sdk/utils/logger/beauty_logger.py
alicia_d_sdk/utils/vislab/__init__.py
alicia_d_sdk/utils/vislab/trajectory.py
alicia_d_sdk-6.1.0b1.dist-info/METADATA
alicia_d_sdk-6.1.0b1.dist-info/WHEEL
alicia_d_sdk-6.1.0b1.dist-info/top_level.txt
alicia_d_sdk-6.1.0b1.dist-info/RECORD
