Metadata-Version: 2.4
Name: alicia_d_sdk
Version: 6.1.0b1
Summary: Python SDK for controlling the Alicia D robotic arm.
Author-email: Synria Robotics <support@synriarobotics.ai>
Project-URL: Homepage, https://github.com/Synria-Robotics/Alicia-D-SDK
Keywords: robotics,robotic-arm,alicia-d,sdk,serial-communication
Classifier: Development Status :: 4 - Beta
Classifier: Intended Audience :: Developers
Classifier: Intended Audience :: Education
Classifier: Intended Audience :: Science/Research
Classifier: License :: OSI Approved :: MIT License
Classifier: Programming Language :: Python :: 3
Classifier: Operating System :: OS Independent
Classifier: Topic :: Software Development :: Libraries :: Python Modules
Classifier: Topic :: System :: Hardware :: Hardware Drivers
Classifier: Topic :: Scientific/Engineering
Requires-Python: >=3.7
Requires-Dist: pyserial>=3.0
Requires-Dist: numpy>=1.21.0
Requires-Dist: scipy>=1.7.0
Requires-Dist: matplotlib>=3.3.0
Requires-Dist: pyyaml>=6.0
Requires-Dist: omegaconf>=2.3.0
Requires-Dist: websockets==13.1
Requires-Dist: pythoncrc
Requires-Dist: pycrc
Requires-Dist: synria-robocore==1.0.0
Requires-Dist: synriard>=1.0.0
